ZetcodeGuiJiaochengChuyi/README.md
ZetcodeGuiJiaochengChuyi/__init__.py
ZetcodeGuiJiaochengChuyi/__main__.py
ZetcodeGuiJiaochengChuyi/file.epub
ZetcodeGuiJiaochengChuyi/index.html
ZetcodeGuiJiaochengChuyi/css/__init__.py
ZetcodeGuiJiaochengChuyi/css/annotations.css
ZetcodeGuiJiaochengChuyi/css/main.css
ZetcodeGuiJiaochengChuyi/css/normalize.css
ZetcodeGuiJiaochengChuyi/css/popup.css
ZetcodeGuiJiaochengChuyi/font/__init__.py
ZetcodeGuiJiaochengChuyi/font/fontello.eot
ZetcodeGuiJiaochengChuyi/font/fontello.svg
ZetcodeGuiJiaochengChuyi/font/fontello.ttf
ZetcodeGuiJiaochengChuyi/font/fontello.woff
ZetcodeGuiJiaochengChuyi/img/__init__.py
ZetcodeGuiJiaochengChuyi/img/annotator-glyph-sprite.png
ZetcodeGuiJiaochengChuyi/img/annotator-icon-sprite.png
ZetcodeGuiJiaochengChuyi/img/apple-touch-icon.png
ZetcodeGuiJiaochengChuyi/img/cancelfullscreen.png
ZetcodeGuiJiaochengChuyi/img/close.png
ZetcodeGuiJiaochengChuyi/img/fullscreen.png
ZetcodeGuiJiaochengChuyi/img/loader.gif
ZetcodeGuiJiaochengChuyi/img/menu-icon.png
ZetcodeGuiJiaochengChuyi/img/save.png
ZetcodeGuiJiaochengChuyi/img/saved.png
ZetcodeGuiJiaochengChuyi/img/settings-s.png
ZetcodeGuiJiaochengChuyi/img/settings.png
ZetcodeGuiJiaochengChuyi/img/star.png
ZetcodeGuiJiaochengChuyi/js/__init__.py
ZetcodeGuiJiaochengChuyi/js/epub.js
ZetcodeGuiJiaochengChuyi/js/epub.min.js
ZetcodeGuiJiaochengChuyi/js/epub.min.map
ZetcodeGuiJiaochengChuyi/js/hooks.min.js
ZetcodeGuiJiaochengChuyi/js/hooks.min.map
ZetcodeGuiJiaochengChuyi/js/reader.js
ZetcodeGuiJiaochengChuyi/js/reader.js.map
ZetcodeGuiJiaochengChuyi/js/reader.min.js
ZetcodeGuiJiaochengChuyi/js/reader.min.map
ZetcodeGuiJiaochengChuyi/js/hooks/__init__.py
ZetcodeGuiJiaochengChuyi/js/hooks/extensions/__init__.py
ZetcodeGuiJiaochengChuyi/js/hooks/extensions/highlight.js
ZetcodeGuiJiaochengChuyi/js/libs/__init__.py
ZetcodeGuiJiaochengChuyi/js/libs/jquery.min.js
ZetcodeGuiJiaochengChuyi/js/libs/localforage.min.js
ZetcodeGuiJiaochengChuyi/js/libs/screenfull.js
zetcode_gui_jiaocheng_chuyi-2024.3.5.0.dist-info/METADATA
zetcode_gui_jiaocheng_chuyi-2024.3.5.0.dist-info/WHEEL
zetcode_gui_jiaocheng_chuyi-2024.3.5.0.dist-info/entry_points.txt
zetcode_gui_jiaocheng_chuyi-2024.3.5.0.dist-info/top_level.txt
zetcode_gui_jiaocheng_chuyi-2024.3.5.0.dist-info/RECORD
